TMO4CT/__init__.py
TMO4CT/algorithm.py
TMO4CT/tools.py
TMO4CT-0.6.data/scripts/TMO4CT_cli.py
TMO4CT-0.6.dist-info/DESCRIPTION.rst
TMO4CT-0.6.dist-info/METADATA
TMO4CT-0.6.dist-info/RECORD
TMO4CT-0.6.dist-info/WHEEL
TMO4CT-0.6.dist-info/metadata.json
TMO4CT-0.6.dist-info/top_level.txt
